cerebral_lstm/__init__.py
cerebral_lstm-1.1.1.dist-info/METADATA
cerebral_lstm-1.1.1.dist-info/WHEEL
cerebral_lstm-1.1.1.dist-info/top_level.txt
cerebral_lstm-1.1.1.dist-info/RECORD
