Metadata-Version: 2.1
Name: cerebral_lstm
Version: 1.1.1
Summary: A PyTorch implementation of Cerebral LSTM: A Better Alternative for Single- and Multi-Stacked LSTM Cell-Based RNNs.
Home-page: https://github.com/mr-ravin/cerebral_lstm
Author: Ravin Kumar
Author-email: mr.ravin_kumar@hotmail.com
License: MIT
Project-URL: Bug Tracker, https://github.com/mr-ravin/cerebral_lstm/issues
Project-URL: Documentation, https://github.com/mr-ravin/cerebral_lstm#readme
Keywords: deep learning,lstm,recurrent neural networks,pytorch,sequence modeling,cerebral lstm,rnn
Classifier: Programming Language :: Python :: 3
Classifier: License :: OSI Approved :: MIT License
Classifier: Operating System :: OS Independent
Classifier: Intended Audience :: Science/Research
Classifier: Topic :: Scientific/Engineering :: Artificial Intelligence
Requires-Python: >=3.7
Requires-Dist: torch >=1.10.0
